lrtree/__init__.py
lrtree/discretization.py
lrtree/fit.py
lrtree/generate_data.py
lrtree/logreg.py
lrtree/predict.py
lrtree/_command_line/__init__.py
lrtree/_command_line/consistency.py
lrtree/_command_line/realdataopen.py
lrtree-1.0.4.dist-info/LICENSE
lrtree-1.0.4.dist-info/METADATA
lrtree-1.0.4.dist-info/WHEEL
lrtree-1.0.4.dist-info/entry_points.txt
lrtree-1.0.4.dist-info/top_level.txt
lrtree-1.0.4.dist-info/RECORD
