Metadata-Version: 2.1
Name: lrtree
Version: 1.0.4
Summary: lrtree: logistic regression trees
Home-page: https://adimajo.github.io/lrtree
Author: Adrien Ehrhardt, Dmitry Gaynullin, Elise Bayraktar
Author-email: Groupe-recherche-operationnelle.GRO@credit-agricole-sa.fr
Classifier: Programming Language :: Python :: 3
Classifier: Operating System :: OS Independent
License-File: LICENSE
Requires-Dist: loguru
Requires-Dist: numpy
Requires-Dist: pandas
Requires-Dist: scikit-learn (>=1.0)
Requires-Dist: tqdm
Provides-Extra: scripts
Requires-Dist: matplotlib ; extra == 'scripts'
Requires-Dist: tikzplotlib ; extra == 'scripts'
Requires-Dist: kaggle ; extra == 'scripts'
